callable_pip/__init__.py
callable_pip-2.0.0.dist-info/LICENSE
callable_pip-2.0.0.dist-info/WHEEL
callable_pip-2.0.0.dist-info/METADATA
callable_pip-2.0.0.dist-info/RECORD
