Metadata-Version: 2.3
Name: callable-pip
Version: 2.0.0
Summary: callable-pip patches 'pip' to add 'pip.main()'
Author-email: Stephen Rosen <sirosen0@gmail.com>
Classifier: Development Status :: 5 - Production/Stable
Classifier: Intended Audience :: Developers
Classifier: License :: OSI Approved :: MIT License
Classifier: Operating System :: OS Independent
Project-URL: Homepage, https://github.com/sirosen/callable-pip
